xlsToCsv/__init__.py
xlsToCsv/xlsToCsv.py
xlsToCsv-0.1.0.dist-info/LICENSE
xlsToCsv-0.1.0.dist-info/METADATA
xlsToCsv-0.1.0.dist-info/WHEEL
xlsToCsv-0.1.0.dist-info/top_level.txt
xlsToCsv-0.1.0.dist-info/RECORD
