Metadata-Version: 2.1
Name: xlsToCsv
Version: 0.1.0
Summary: This script converts excel files to CSV
Home-page: https://github.com/atul-shr/xlsToCsv
Author: Atul Sharma
Author-email: atulsharma131@gmail.com
License: UNKNOWN
Platform: UNKNOWN
Classifier: Programming Language :: Python :: 3
Classifier: License :: OSI Approved :: MIT License
Classifier: Operating System :: OS Independent
Requires-Python: >=3.6
